setup.py
tabs/__init__.py
tabs/tables.py
tabs/tabs.py
tabs.egg-info/PKG-INFO
tabs.egg-info/SOURCES.txt
tabs.egg-info/dependency_links.txt
tabs.egg-info/requires.txt
tabs.egg-info/top_level.txt