Metadata-Version: 1.1
Name: tabs
Version: 0.6.3
Summary: Tabs - Import tables in a consistent, maintainable, and readable way
Home-page: https://github.com/ohenrik/tabs
Author: Ole Henrik Skogstrøm
Author-email: ole@amplify.no
License: UNKNOWN
Platform: UNKNOWN
Classifier: Development Status :: 2 - Pre-Alpha
